music_melodicdevice/__init__.py
music_melodicdevice/music_melodicdevice.py
music_melodicdevice-0.3.0.dist-info/licenses/LICENSE
music_melodicdevice-0.3.0.dist-info/METADATA
music_melodicdevice-0.3.0.dist-info/WHEEL
music_melodicdevice-0.3.0.dist-info/top_level.txt
music_melodicdevice-0.3.0.dist-info/RECORD
