Metadata-Version: 2.4
Name: music_melodicdevice
Version: 0.3.0
Summary: Apply chromatic and diatonic transformations to music notes
Author-email: Gene Boggs <gene.boggs@gmail.com>
License:                     GNU GENERAL PUBLIC LICENSE
Project-URL: Homepage, https://github.com/ology/Python-Music-MelodicDevice
Project-URL: Repository, https://github.com/ology/Python-Music-MelodicDevice.git
Project-URL: Issues, https://github.com/ology/Python-Music-MelodicDevice/issues
Classifier: Development Status :: 2 - Pre-Alpha
Classifier: Programming Language :: Python
Classifier: Programming Language :: Python :: 3
Classifier: Programming Language :: Python :: 3.9
Classifier: Programming Language :: Python :: 3.10
Classifier: Programming Language :: Python :: 3.11
Classifier: Programming Language :: Python :: 3.12
Requires-Python: >=3.9
License-File: LICENSE
Dynamic: license-file
